exshell/__init__.py
exshell/exshell.py
exshell/exshell_builder.py
exshell/wizards/__init__.py
exshell/wizards/please_input_excel_application_path.py
exshell-2025042901.0.1.dist-info/METADATA
exshell-2025042901.0.1.dist-info/WHEEL
exshell-2025042901.0.1.dist-info/licenses/LICENSE
exshell-2025042901.0.1.dist-info/RECORD
